llama_index/py.typed
llama_index/vector_stores/redis/__init__.py
llama_index/vector_stores/redis/base.py
llama_index/vector_stores/redis/schema.py
llama_index/vector_stores/redis/utils.py
llama_index_vector_stores_redis-0.6.2.dist-info/METADATA
llama_index_vector_stores_redis-0.6.2.dist-info/WHEEL
llama_index_vector_stores_redis-0.6.2.dist-info/licenses/LICENSE
llama_index_vector_stores_redis-0.6.2.dist-info/RECORD
